odoo/addons/sale_mrp_bom/README.rst
odoo/addons/sale_mrp_bom/__init__.py
odoo/addons/sale_mrp_bom/__manifest__.py
odoo/addons/sale_mrp_bom/i18n/es.po
odoo/addons/sale_mrp_bom/i18n/hr.po
odoo/addons/sale_mrp_bom/i18n/it.po
odoo/addons/sale_mrp_bom/i18n/nl.po
odoo/addons/sale_mrp_bom/i18n/nl_NL.po
odoo/addons/sale_mrp_bom/i18n/sale_mrp_bom.pot
odoo/addons/sale_mrp_bom/models/__init__.py
odoo/addons/sale_mrp_bom/models/procurement_group.py
odoo/addons/sale_mrp_bom/models/sale_order_line.py
odoo/addons/sale_mrp_bom/models/stock_move.py
odoo/addons/sale_mrp_bom/readme/CONFIGURE.md
odoo/addons/sale_mrp_bom/readme/CONTRIBUTORS.md
odoo/addons/sale_mrp_bom/readme/CREDITS.md
odoo/addons/sale_mrp_bom/readme/DESCRIPTION.md
odoo/addons/sale_mrp_bom/readme/INSTALL.md
odoo/addons/sale_mrp_bom/readme/ROADMAP.md
odoo/addons/sale_mrp_bom/readme/USAGE.md
odoo/addons/sale_mrp_bom/security/security.xml
odoo/addons/sale_mrp_bom/static/description/icon.png
odoo/addons/sale_mrp_bom/static/description/index.html
odoo/addons/sale_mrp_bom/static/description/manufacturing_order_1.png
odoo/addons/sale_mrp_bom/static/description/sale_order_1.png
odoo/addons/sale_mrp_bom/tests/__init__.py
odoo/addons/sale_mrp_bom/tests/test_sale_mrp_bom.py
odoo/addons/sale_mrp_bom/tests/test_sale_mrp_bom_multi_line.py
odoo/addons/sale_mrp_bom/views/sale_order.xml
odoo/addons/sale_mrp_bom/views/sale_order_line.xml
odoo_addon_sale_mrp_bom-18.0.1.0.0.7.dist-info/METADATA
odoo_addon_sale_mrp_bom-18.0.1.0.0.7.dist-info/WHEEL
odoo_addon_sale_mrp_bom-18.0.1.0.0.7.dist-info/top_level.txt
odoo_addon_sale_mrp_bom-18.0.1.0.0.7.dist-info/RECORD
